HypixelLib/Mojang.py
HypixelLib/__init__.py
HypixelLib/exceptions.py
HypixelLib/hypixel.py
HypixelLib/hypixelplayer.py
HypixelLib/objects.py
HypixelLib/profile.py
HypixelLib/utils.py
HypixelLib/games/__init__.py
HypixelLib/games/bedwars.py
HypixelLib-2022.1.14.6.dist-info/License
HypixelLib-2022.1.14.6.dist-info/METADATA
HypixelLib-2022.1.14.6.dist-info/WHEEL
HypixelLib-2022.1.14.6.dist-info/top_level.txt
HypixelLib-2022.1.14.6.dist-info/RECORD
