Metadata-Version: 2.1
Name: HypixelLib
Version: 2022.1.14.6
Summary: A Package for the Hypixel API
Home-page: https://github.com/Kejax/Hypixel-Lib
Author: Kejax
Author-email: outstanding.games.studios@googlemail.com
License: UNKNOWN
Project-URL: Documentation, https://hypixel-lib.readthedocs.io/de/latest/
Platform: UNKNOWN
Classifier: Programming Language :: Python :: 3
Classifier: License :: OSI Approved :: MIT License
Classifier: Operating System :: OS Independent
Requires-Python: >=3.6
License-File: License
